{
  "waffles": {
    "quantity": 6,
    "ingredients": {
      "flour": 600,
      "sugar": 100,
      "eggs": 6,
      "milk": 750,
      "butter": 150,
      "yeast": 15
    },
    "units": {
      "flour": "g",
      "sugar": "g",
      "eggs": "unit",
      "milk": "ml",
      "butter": "g",
      "yeast": "g"
    },
    "instructions": [
      "Mix flour, sugar, salt, and yeast in a bowl.",
      "Add eggs, milk, and melted butter. Mix well until you get a smooth batter.",
      "Let the batter rest for 30 minutes.",
      "Heat the waffle iron and pour a ladle of batter into each mold.",
      "Cook the waffles until they are golden and crispy.",
      "Serve hot with maple syrup, powdered sugar, or fruits."
    ]
  },
  "Crepes": {
    "quantity": 4,
    "ingredients": {
      "flour": 110,
      "sugar": 70,
      "eggs": 4,
      "milk": 666,
      "butter": 78,
      "yeast": 5
    },
    "units": {
      "flour": "g",
      "sugar": "g",
      "eggs": "unit",
      "milk": "ml",
      "butter": "g",
      "yeast": "g"
    },
    "instructions": [
      "jflskdjslfqjkdlfkqlkfmlqskfmlqksmfù"
    ]
  }
}